{
    "id": "751606441315401848",
    "name": "Cry",
    "description": "Nelly cries profusely as her eyes sparkle",
    "tags": [
        "nelly",
        "cry",
        "cries",
        "crying",
        "sob",
        "sobbing",
        "sad",
        "upset",
        "feelsbad",
        "feelsbadman",
        ":<",
        ":(",
        ":[",
        "😥",
        "😢",
        "😭",
        "):",
        ":c",
        ":'(",
        "t-t",
        "T_T",
        "tear",
        ":sad",
        ":tear",
        ":cry",
        ":crying",
        "chorando",
        "triste",
        "pain",
        "sadness"
    ],
    "type": 1,
    "format_type": 3,
    "asset": "",
    "pack_id": "751604115435421716",
    "sort_value": 4
}